robel/__init__.py
robel/robot_env.py
robel/robot_env_test.py
robel/components/__init__.py
robel/components/base.py
robel/components/base_test.py
robel/components/builder.py
robel/components/builder_test.py
robel/components/robot/__init__.py
robel/components/robot/builder.py
robel/components/robot/dynamixel_client.py
robel/components/robot/dynamixel_client_test.py
robel/components/robot/dynamixel_robot.py
robel/components/robot/dynamixel_robot_test.py
robel/components/robot/dynamixel_utils.py
robel/components/robot/group_config.py
robel/components/robot/group_config_test.py
robel/components/robot/hardware_robot.py
robel/components/robot/hardware_robot_test.py
robel/components/robot/robot.py
robel/components/robot/robot_test.py
robel/components/tracking/__init__.py
robel/components/tracking/builder.py
robel/components/tracking/group_config.py
robel/components/tracking/hardware_tracker.py
robel/components/tracking/phasespace_tracker.py
robel/components/tracking/tracker.py
robel/components/tracking/vr_tracker.py
robel/components/tracking/utils/__init__.py
robel/components/tracking/utils/coordinate_system.py
robel/components/tracking/virtual_reality/__init__.py
robel/components/tracking/virtual_reality/client.py
robel/components/tracking/virtual_reality/device.py
robel/components/tracking/virtual_reality/poses.py
robel/dclaw/__init__.py
robel/dclaw/base_env.py
robel/dclaw/pose.py
robel/dclaw/pose_test.py
robel/dclaw/screw.py
robel/dclaw/screw_test.py
robel/dclaw/scripted_reset.py
robel/dclaw/turn.py
robel/dclaw/turn_test.py
robel/dclaw/assets/dclaw3xh_valve3_v0.xml
robel/dkitty/__init__.py
robel/dkitty/avoid.py
robel/dkitty/base_env.py
robel/dkitty/orient.py
robel/dkitty/orient_test.py
robel/dkitty/push.py
robel/dkitty/stand.py
robel/dkitty/stand_test.py
robel/dkitty/walk.py
robel/dkitty/walk_test.py
robel/dkitty/assets/dkitty_avoid-v0.xml
robel/dkitty/assets/dkitty_orient-v0.xml
robel-0.1.2.dist-info/METADATA
robel-0.1.2.dist-info/RECORD
robel-0.1.2.dist-info/WHEEL
robel-0.1.2.dist-info/top_level.txt
