Metadata-Version: 2.1
Name: robel
Version: 0.1.2
Summary: Robotics reinforcement learning benchmark tasks with cost-effective robots.
Home-page: UNKNOWN
License: Apache 2.0
Platform: UNKNOWN
Classifier: Programming Language :: Python :: 3
Classifier: License :: OSI Approved :: Apache Software License
Classifier: Topic :: Scientific/Engineering :: Artificial Intelligence
Classifier: Intended Audience :: Science/Research
Requires-Python: >=3.5.3
Requires-Dist: gym (<0.14.0,>=0.11.0)
Requires-Dist: mujoco-py (<2.1,>2.0)
Requires-Dist: numpy (>=1.10.4)
Requires-Dist: transforms3d (>=0.3.0<0.4)
